BRAD/__init__.py
BRAD/agent.py
BRAD/bradllm.py
BRAD/chat.py
BRAD/coder.py
BRAD/config/.ipynb_checkpoints/configSeaborn-checkpoint.json
BRAD/config/.ipynb_checkpoints/configSnakemake-checkpoint.json
BRAD/config/config.json
BRAD/constants.py
BRAD/endpoints.py
BRAD/enrichr.py
BRAD/gene_ontology.py
BRAD/geneDatabaseCaller.py
BRAD/helperData/.ipynb_checkpoints/gene_list-checkpoint.txt
BRAD/helperData/.ipynb_checkpoints/ggetEnrichrDatabases-checkpoint.tsv
BRAD/helperData/gene_list.txt
BRAD/helperData/ggetEnrichrDatabases.tsv
BRAD/justchat.py
BRAD/llms.py
BRAD/log.py
BRAD/planner.py
BRAD/promptTemplates.py
BRAD/pythonCaller.py
BRAD/rag.py
BRAD/router.py
BRAD/routers/code.txt
BRAD/routers/data.txt
BRAD/routers/enrichr.txt
BRAD/routers/load.txt
BRAD/routers/matlab.txt
BRAD/routers/planner.txt
BRAD/routers/python.txt
BRAD/routers/rag.txt
BRAD/routers/router.txt
BRAD/routers/scrape.txt
BRAD/routers/sns.txt
BRAD/routers/table.txt
BRAD/routers/write.txt
BRAD/scraper.py
BRAD/utils.py
BRAD/writer.py
brad_agent-0.1.33.dist-info/LICENSE
brad_agent-0.1.33.dist-info/METADATA
brad_agent-0.1.33.dist-info/WHEEL
brad_agent-0.1.33.dist-info/RECORD
