Metadata-Version: 2.3
Name: BRAD-Agent
Version: 0.1.33
Summary: This package connects large language models with bioinformatics workflows.
Author: Joshua Pickard
Author-email: jpic@umich.edu
Requires-Python: >=3.10
Classifier: Programming Language :: Python :: 3
Classifier: License :: OSI Approved :: MIT License
Classifier: Operating System :: OS Independent
Requires-Dist: Requests
Requires-Dist: beautifulsoup4 (==4.12.3)
Requires-Dist: chromadb (==0.5.0)
Requires-Dist: gget (==0.28.6)
Requires-Dist: ipython
Requires-Dist: langchain_chroma (==0.1.1)
Requires-Dist: langchain_community (==0.2.4)
Requires-Dist: langchain_core (==0.2.5)
Requires-Dist: langchain_nvidia_ai_endpoints (==0.1.1)
Requires-Dist: langchain_text_splitters
Requires-Dist: semantic-router (==0.0.46)
Requires-Dist: torch
Requires-Dist: transformers
Project-URL: Bug Tracker, https://github.com/Jpickard1/RAG-DEV
Project-URL: Homepage, https://github.com/Jpickard1/RAG-DEV
